README.md
setup.py
japan_address/__init__.py
japan_address/japan_address.py
japan_address.egg-info/PKG-INFO
japan_address.egg-info/SOURCES.txt
japan_address.egg-info/dependency_links.txt
japan_address.egg-info/top_level.txt
japan_address/data/local_government.csv
tests/__init__.py
tests/test_japan_address.py