Metadata-Version: 2.1
Name: japan-address
Version: 0.7.2
Summary: Japan address utilities
Home-page: https://github.com/kzthrk/japan_address
Author: kzthrk
Author-email: kzthrk@gmail.com
License: MIT
Keywords: japan,japanese,address
Platform: UNKNOWN
Classifier: Programming Language :: Python :: 3.8
Classifier: License :: OSI Approved :: MIT License
Classifier: Operating System :: OS Independent
